zmqdecorators/zmq_utilities.py
zmqdecorators/bonjour_utilities.py
zmqdecorators/__init__.py
zmqdecorators-0.7.3.dist-info/WHEEL
zmqdecorators-0.7.3.dist-info/DESCRIPTION.rst
zmqdecorators-0.7.3.dist-info/top_level.txt
zmqdecorators-0.7.3.dist-info/METADATA
zmqdecorators-0.7.3.dist-info/metadata.json
zmqdecorators-0.7.3.dist-info/RECORD
