Metadata-Version: 2.0
Name: zmqdecorators
Version: 0.7.3
Summary: Decorators for pyZMQ to make it almost as easy to use a DBUS
Home-page: https://github.com/rambo/python-zmqdecorators
Author: Eero "rambo" af Heurlin
Author-email: rambo@iki.fi
License: GNU LGPL
Platform: UNKNOWN
Requires-Dist: tornado (>=2.0)
Requires-Dist: pyzmq (>=2.0)
Requires-Dist: pybonjour (>=1.1)
